nlgmetricverse/__init__.py
nlgmetricverse/cli.py
nlgmetricverse/collator.py
nlgmetricverse/core.py
nlgmetricverse/data_loader.py
nlgmetricverse/definitions.py
nlgmetricverse/tokenizer.py
nlgmetricverse/meta_eval/__init__.py
nlgmetricverse/meta_eval/metric_human_correlation.py
nlgmetricverse/meta_eval/metrics_correlation.py
nlgmetricverse/meta_eval/performance_comparison.py
nlgmetricverse/metrics/__init__.py
nlgmetricverse/metrics/_core/__init__.py
nlgmetricverse/metrics/_core/auto.py
nlgmetricverse/metrics/_core/auxiliary.py
nlgmetricverse/metrics/_core/base.py
nlgmetricverse/metrics/_core/utils.py
nlgmetricverse/metrics/abstractness/__init__.py
nlgmetricverse/metrics/abstractness/abstractness.py
nlgmetricverse/metrics/abstractness/abstractness_planet.py
nlgmetricverse/metrics/accuracy/__init__.py
nlgmetricverse/metrics/accuracy/accuracy.py
nlgmetricverse/metrics/accuracy/accuracy_planet.py
nlgmetricverse/metrics/aun/__init__.py
nlgmetricverse/metrics/aun/aun.py
nlgmetricverse/metrics/aun/aun_planet.py
nlgmetricverse/metrics/bartscore/__init__.py
nlgmetricverse/metrics/bartscore/bartscore.py
nlgmetricverse/metrics/bartscore/bartscore_planet.py
nlgmetricverse/metrics/bertscore/__init__.py
nlgmetricverse/metrics/bertscore/bertscore.py
nlgmetricverse/metrics/bertscore/bertscore_planet.py
nlgmetricverse/metrics/bleu/__init__.py
nlgmetricverse/metrics/bleu/bleu.py
nlgmetricverse/metrics/bleu/bleu_planet.py
nlgmetricverse/metrics/bleurt/__init__.py
nlgmetricverse/metrics/bleurt/bleurt.py
nlgmetricverse/metrics/bleurt/bleurt_planet.py
nlgmetricverse/metrics/carburacy/__init__.py
nlgmetricverse/metrics/carburacy/carburacy.py
nlgmetricverse/metrics/carburacy/carburacy_planet.py
nlgmetricverse/metrics/cer/__init__.py
nlgmetricverse/metrics/cer/cer.py
nlgmetricverse/metrics/cer/cer_planet.py
nlgmetricverse/metrics/chrf/__init__.py
nlgmetricverse/metrics/chrf/chrf.py
nlgmetricverse/metrics/chrf/chrf_planet.py
nlgmetricverse/metrics/cider/__init__.py
nlg_metricverse-0.9.9.dist-info/LICENSE
nlg_metricverse-0.9.9.dist-info/METADATA
nlg_metricverse-0.9.9.dist-info/WHEEL
nlg_metricverse-0.9.9.dist-info/entry_points.txt
nlg_metricverse-0.9.9.dist-info/top_level.txt
nlg_metricverse-0.9.9.dist-info/RECORD
