Metadata-Version: 2.1
Name: nlg-metricverse
Version: 0.9.9
Summary: An End-to-End Library for Evaluating Natural Language Generation.
Home-page: https://github.com/disi-unibo-nlp/nlg-metricverse
Download-URL: https://github.com/disi-unibo-nlp/nlg-metricverse/archive/refs/tags/0.9.9.tar.gz
Author: DISI UniBo NLP
Author-email: disi.unibo.nlp@gmail.com
License: MIT
Keywords: natural-language-processing natural-language-generation nlg-evaluation metrics language-models visualization python pytorch
Classifier: Development Status :: 3 - Alpha
Classifier: Operating System :: OS Independent
Classifier: Intended Audience :: Developers
Classifier: Intended Audience :: Science/Research
Classifier: License :: OSI Approved :: MIT License
Classifier: Programming Language :: Python :: 3
Classifier: Programming Language :: Python :: 3.7
Classifier: Programming Language :: Python :: 3.8
Classifier: Programming Language :: Python :: 3.9
Classifier: Topic :: Software Development :: Libraries
Classifier: Topic :: Software Development :: Libraries :: Python Modules
Classifier: Topic :: Education
Classifier: Topic :: Scientific/Engineering
Classifier: Topic :: Scientific/Engineering :: Artificial Intelligence
Requires-Python: >=3.7
License-File: LICENSE
Requires-Dist: datasets (<2.10,>=2.9)
Requires-Dist: fire (>=0.4.0)
Requires-Dist: nltk (<3.7.1,>=3.6.6)
Requires-Dist: numpy (>=1.21.0)
Requires-Dist: pandas (>=1.1.5)
Requires-Dist: rouge-score (==0.1.2)
Requires-Dist: setuptools (>=65.5.1)
Requires-Dist: requests (>=2.27.1)
Requires-Dist: click (==8.1.3)
Requires-Dist: syllables (>=1.0.3)
Requires-Dist: typing (>=3.7.4.3)
Requires-Dist: packaging (>=21.3)
Requires-Dist: scipy (>=1.9)
Requires-Dist: matplotlib (>=3.5.1)
Requires-Dist: textstat (>=0.7.3)
Requires-Dist: codecarbon (==2.1.4)
Requires-Dist: validators (>=0.20.0)
Requires-Dist: seaborn (>=0.12.0)
Requires-Dist: torch (>=1.12.0)
Requires-Dist: transformers (>=4.24.0)
Requires-Dist: bert-score (>=0.3.11)
Requires-Dist: tqdm (>=4.64.1)
Requires-Dist: evaluate (>=0.4)
Requires-Dist: pyemd (>=0.5.1)
Requires-Dist: ipython (>=7.16.1)
Requires-Dist: scikit-learn
Provides-Extra: dev
Requires-Dist: black (==21.7b0) ; extra == 'dev'
Requires-Dist: deepdiff (==5.5.0) ; extra == 'dev'
Requires-Dist: flake8 (==3.9.2) ; extra == 'dev'
Requires-Dist: isort (==5.9.2) ; extra == 'dev'
Requires-Dist: pytest (>=7.0.1) ; extra == 'dev'
Requires-Dist: pytest-cov (>=3.0.0) ; extra == 'dev'
Requires-Dist: pytest-timeout (>=2.1.0) ; extra == 'dev'
Requires-Dist: pytorch-transformers (==1.2.0) ; extra == 'dev'
Requires-Dist: wget (==3.2) ; extra == 'dev'
